Metadata-Version: 2.1
Name: pycereal
Version: 1.0
Summary: A simple object and Django model JSON serializer
Home-page: https://github.com/istrategylabs/cereal
Author: Jeremy Carbaugh
Author-email: jeremy@isl.co
License: BSD
Platform: any
Classifier: Development Status :: 4 - Beta
Classifier: Intended Audience :: Developers
Classifier: Operating System :: OS Independent
Classifier: Programming Language :: Python
Classifier: Topic :: Software Development :: Libraries :: Python Modules
